{"www.cdiscount.com": -1, "fr.shopping.rakuten.com": -1, "www.automobile.fr": 2, "www.societe.com": -1, "www.jeuxvideo.com": 10, "www.allocine.fr": 6, "forum.doctissimo.fr": 5, "dictionnaire.reverso.net": 3, "www.conforama.fr": -1, "www.marmiton.org": 12, "context.reverso.net": 3, "m.jeuxvideo.com": 10, "www.ouest-france.fr": -1, "mobile-dictionary.reverso.net": 3, "www.lachainemeteo.com": 11, "www.senscritique.com": 6, "www.cuisineaz.com": 12, "www.purepeople.com": 9, "www.listesdemots.net": 3, "www.linternaute.fr": 3, "www.tameteo.com": 11, "www.ladepeche.fr": 11, "www.avendrealouer.fr": 7, "m.programme-tv.net": 9, "chefsimon.com": 12, "www.doctissimo.fr": 5, "www.programme-tv.net": 9, "www.commentcamarche.net": -1, "dirigeant.societe.com": -1, "www.femmeactuelle.fr": -1, "www.750g.com": 12, "www.boursorama.com": 1, "www.babelio.com": -1, "www.sto.cx": -1, "www.autoscout24.fr": 2, "www.cuisineactuelle.fr": 12, "www.20minutes.fr": -1, "annuaire.118712.fr": -1, "m.mobile.de": 2, "www.wuxiaworld.com": -1, "www.meteo60.fr": 11, "www.leparisien.fr": -1, "www.lemonde.fr": -1, "www.supersoluce.com": 10, "clients.cdiscount.com": -1, "www.seloger.com": 7, "www.lesnumeriques.com": -1, "www.gala.fr": 9, "www.journaldesfemmes.fr": -1, "mots-croises.tazzaz.com": -1, "www.ebay-kleinanzeigen.de": 2, "cuisine.journaldesfemmes.fr": 12, "www.letelegramme.fr": -1, "www.2ememain.be": 2, "www.meteoblue.com": 11, "www.lesechos.fr": -1, "www.franceculture.fr": -1, "paroles2chansons.lemonde.fr": -1, "www.linternaute.com": -1, "www.capital.fr": -1, "www.sudouest.fr": -1, "forum.parents.fr": 5, "dict.leo.org": 3, "www.lequipe.fr": 8, "droit-finances.commentcamarche.com": -1, "www.beaute-test.com": -1, "grossesse.aufeminin.com": -1, "www.voici.fr": 9, "www.marinetraffic.com": -1, "www.mobile.de": 2, "www.dailymotion.com": -1, "www.rtl.fr": -1, "1mot.net": 3, "www.autoplus.fr": 2, "euw.op.gg": 10, "www.lavoixdunord.fr": -1, "www.francebleu.fr": -1, "www.meteocity.com": 11, "entreprises.lefigaro.fr": -1, "jeu.info": -1, "voyageforum.com": -1, "bebes.aufeminin.com": -1, "www.babycenter.fr": -1, "m.ebay-kleinanzeigen.de": 2, "www.theguardian.com": -1, "www.telestar.fr": 9, "www.clubic.com": -1, "www.telerama.fr": 6, "www.huffingtonpost.fr": -1, "www.lamontagne.fr": -1, "fr.viadeo.com": -1, "www.franceinter.fr": -1, "www.go-sport.com": -1, "www.melty.fr": 9, "www.horairesdouverture24.fr": -1, "m.meteocity.com": 11, "www.topsante.com": 5, "www.millenium.org": 10, "www.futbin.com": 8, "www.yeggi.com": -1, "www.trombi.com": 4, "amour-couple.aufeminin.com": -1, "forums.cnetfrance.fr": -1, "deskgram.co": 4, "www.apreslachat.com": -1, "saveig.org": 4, "www.footmercato.net": 8, "www.nouvelobs.com": -1, "fr.pons.com": 3, "www.midilibre.fr": -1, "www.fnaim.fr": 7, "www.topito.com": -1, "www.turbo.fr": 2, "www.dailymail.co.uk": -1, "www.closermag.fr": -1, "www.marktplaats.nl": 2, "cally.com": -1, "www.aufeminin.com": -1, "www.frandroid.com": -1, "madame.lefigaro.fr": -1, "www.secondechance.org": -1, "www.lefigaro.fr": -1, "www.gamekult.com": 10, "www.leparking-moto.fr": -1, "brocabrac.fr": -1, "www.fourchette-et-bikini.fr": 12, "citations.ouest-france.fr": -1, "www.forums.supertoinette.com": 12, "fr.soccerway.com": 8, "www.lalanguefrancaise.com": 3, "www.purebreak.com": 9, "investir.lesechos.fr": 1, "www.readlightnovel.org": -1, "www.deco.fr": -1, "www.ohmymag.com": -1, "leconjugueur.lefigaro.fr": 3, "www.gralon.net": -1, "www.lindependant.fr": 11, "webmail1p.orange.fr": 0, "conjugueur.reverso.net": 3, "www.lesanciennes.com": 2, "www.numeroinconnu.fr": -1, "www.chartsinfrance.net": -1, "picpanzee.com": 4, "beaute.aufeminin.com": -1, "www.paris-normandie.fr": -1, "fr.bab.la": 3, "www.01net.com": -1, "www.numerama.com": -1, "www.gumtree.com": 2, "www.autoscout24.de": 2, "business.lesechos.fr": -1, "www.journaldunet.com": -1, "etudiant.aujourdhui.fr": -1, "blitz.gg": 10, "cuisine.aufeminin.com": 12, "www.vice.com": -1, "www.developpez.net": -1, "www.hurriyet.com.tr": -1, "www.pcastuces.com": -1, "www.grazia.fr": -1, "www.le-dictionnaire.com": 3, "www.francemusique.fr": -1, "www.onmeda.fr": 5, "rencontre-ados.net": 4, "www.milliyet.com.tr": -1, "www.boiteachansons.net": -1, "www.auto-moto.com": 2, "www.boursier.com": 1, "www.maison-travaux.fr": -1, "m.huffingtonpost.fr": -1, "www.mystalk.net": 4, "fr.blastingnews.com": -1, "www.justwatch.com": -1, "www.2dehands.be": 2, "webmail1k.orange.fr": 0, "www.supertoinette.com": 12, "de.pons.com": 3, "www.parents.fr": -1, "webmail1e.orange.fr": 0, "www.zonebourse.com": 1, "www.businessinsider.fr": -1, "webmail1c.orange.fr": 0, "www.radio.fr": -1, "www.momes.net": -1, "webmail1m.orange.fr": 0, "www.programme.tv": 9, "odelices.ouest-france.fr": 12, "www.ecranlarge.com": 6, "www.toopics.com": -1, "webmail1j.orange.fr": 0, "programme-tv.leparisien.fr": 9, "television.telerama.fr": 9, "test.femmeactuelle.fr": -1, "www.geo.fr": -1, "photo.femmeactuelle.fr": -1, "webmail1f.orange.fr": 0, "www.okkazeo.com": -1, "marine.meteoconsult.fr": 11, "sante.lefigaro.fr": 5, "www.planeterenault.com": -1, "pikdo.biz": 4, "la-conjugaison.nouvelobs.com": 3, "www.lanouvellerepublique.fr": -1, "programme-tv.orange.fr": 9, "isekaiscan.com": -1, "amelioretasante.com": 5, "www.express.co.uk": -1, "www.santemagazine.fr": -1, "www.football365.fr": 8, "www.cnetfrance.fr": -1, "jardinage.ooreka.fr": -1, "www.wanimo.com": -1, "www.over-blog.com": -1, "meteo.orange.fr": 11, "donnons.org": -1, "travail-vie-pratique.aufeminin.com": -1, "psychologie.aufeminin.com": -1, "agenda-loto.net": 11, "forum.frandroid.com": -1, "gourmand.viepratique.fr": 12, "www.passeportsante.net": 5, "sante-medecine.journaldesfemmes.fr": 5, "vide-greniers.org": -1, "www.shpock.com": -1, "gravitytales.com": -1, "www.breakflip.com": 10, "www.vogue.fr": -1, "www.mesrecettesfaciles.fr": 12, "nospensees.fr": -1, "webmail1n.orange.fr": 0, "maison.aufeminin.com": -1, "famille.aufeminin.com": -1, "www.santeplusmag.com": -1, "www.meteoconsult.fr": 11, "sports.orange.fr": 8, "www.marieclaire.fr": -1, "www.techradar.com": -1, "tendances.orange.fr": -1, "sante.journaldesfemmes.fr": -1, "www.cinetrafic.fr": 6, "www.fifaindex.com": 8, "webmail1g.orange.fr": 0, "www.nicematin.com": -1, "www.consoglobe.com": -1, "actu.orange.fr": -1, "tvmag.lefigaro.fr": 9, "www.goal.com": 8, "video-streaming.orange.fr": -1, "deco.journaldesfemmes.fr": -1, "www.francefootball.fr": 8, "www.thesun.co.uk": -1, "www.atlantico.fr": -1, "www.howtogeek.com": -1, "infolocale.ouest-france.fr": -1, "gaming.gentside.com": 10, "animaux.aufeminin.com": -1, "www.mirror.co.uk": -1, "www.hypnoweb.net": 9, "www.regal.fr": 12, "www.kadinlarkulubu.com": -1, "mariage.aufeminin.com": -1, "www.actualitte.com": -1, "www.duden.de": 3, "abonne.lunion.fr": 11, "www.cdiscountpro.com": -1, "wikidich.com": -1, "www.caminteresse.fr": -1, "www.mobafire.com": 10, "www.mariefrance.fr": -1, "test-personnalite.programme-tv.net": -1, "www.promovacances.com": -1, "mobile.programme.tv": 9, "www.larep.fr": -1, "www.cesoirtv.com": 9, "www.jeux.fr": -1, "amp.melty.fr": 9, "www.rollingstone.com": -1, "cineday.orange.fr": 6, "www.cowcotland.com": -1, "www.autoscout24.com": 2, "astrologie.aufeminin.com": -1, "www.maxisciences.com": -1, "www.lechorepublicain.fr": -1, "start.lesechos.fr": -1, "www.amandinecooking.com": 12, "fr.besoccer.com": 8, "fr.windfinder.com": 11, "gocar.be": 2, "www.immobilienscout24.de": 7, "webmail1h.orange.fr": 0, "recepti.gotvach.bg": 12, "www.sujetdebac.fr": -1, "www.zoover.fr": -1, "dictionary.reverso.net": 3, "www.promoalert.com": -1, "www.lyonne.fr": -1, "www.motoservices.com": -1, "www.abcbourse.com": 1, "www.centrepresseaveyron.fr": -1, "www.dossierfamilial.com": -1, "leparticulier.lefigaro.fr": -1, "fr.classic.wowhead.com": 10, "www.wetteronline.de": 11, "www.e-puzzles.fr": -1, "www.courrierinternational.com": -1, "www.cosmopolitan.fr": -1, "maigrir.aufeminin.com": -1, "www.leberry.fr": -1, "www.elmundo.es": -1, "photo.gala.fr": -1, "www.gerbeaud.com": -1, "www.corsematin.com": -1, "www.lejdc.fr": -1, "www.gqmagazine.fr": -1, "test.gala.fr": -1, "www.coloriez.com": -1, "rankersta.com": 4, "synonyms.reverso.net": 3, "www.serieously.com": 9, "www.1001cocktails.com": 12, "www.magicmaman.com": -1, "en.bab.la": 3, "videos.doctissimo.fr": -1, "www.ukulele-tabs.com": -1, "www.gentside.com": -1, "webmail22.orange.fr": 0, "www.immobilier-france.fr": 7, "www.communes.com": -1, "www.mynet.com": -1, "www.varmatin.com": -1, "bricolage.linternaute.com": -1, "www.psthc.fr": 10, "www.piwox.com": 4, "m.paruvendu.fr": -1, "www.sudinfo.be": -1, "www.grands-meres.net": -1, "m.20minutes.fr": -1, "www.smbc-comics.com": -1, "www.journaldunet.fr": -1, "www.cnnturk.com": -1, "metro.co.uk": -1, "www.laprovence.com": 11, "www.windfinder.com": 11, "www.whathifi.com": -1, "www.sports.fr": 8, "www.lepopulaire.fr": -1, "conseils.radins.com": -1, "m.rtl.be": -1, "ricette.giallozafferano.it": 12, "www.onzemondial.com": 8, "www.gamesradar.com": -1, "streamable.com": -1, "gamewave.fr": -1, "forums.tomshardware.com": -1, "www.actugaming.net": 10, "www.op.gg": 10, "www.viadeo.com": -1, "loisirs.aufeminin.com": -1, "www.bibamagazine.fr": -1, "premium.courrier-picard.fr": -1, "www.livescience.com": -1, "www.warlegend.net": 10, "www.1001pneus.fr": -1, "www.lecker.de": 12, "www.epicetoutlacuisinededany.fr": 12, "swgoh.gg": -1, "dl-file.com": -1, "www.charentelibre.fr": -1, "fr.exchange-rates.org": -1, "www.explorimmoneuf.com": 7, "www.chezvanda.com": 12, "chien.ooreka.fr": -1, "www.transfermarkt.com.tr": 8, "kachelmannwetter.com": 11, "www.pleinevie.fr": -1, "amp.ouest-france.fr": -1, "www.boredpanda.com": -1, "www.mangasail.co": -1, "www.tiempo.com": 11, "www.jeu.fr": -1, "suchen.mobile.de": 2, "m.investir.lesechos.fr": 1, "www.t-online.de": -1, "www.jeuxjeuxjeux.fr": -1, "chirurgie-esthetique.aufeminin.com": -1, "sport.gentside.com": -1, "www.lejournaldelamaison.fr": -1, "www.autoscout24.it": 2, "www.easyvoyage.com": -1, "photo.cuisineactuelle.fr": 12, "mode.aufeminin.com": -1, "nantes.maville.com": -1, "dizionario.reverso.net": 3, "siecledigital.fr": -1, "www.causeur.fr": -1, "bibliobs.nouvelobs.com": -1, "www.gotceleb.com": -1, "construction-maison.ooreka.fr": -1, "mon-partage.fr": -1}